opr/__main__.py
opr/methods.py
opr/objects.py
opr/runtime.py
opr/storage.py
opr/threads.py
opr/utility.py
opr/modules/__init__.py
opr/modules/cmd.py
opr/modules/fnd.py
opr/modules/irc.py
opr/modules/log.py
opr/modules/mod.py
opr/modules/rss.py
opr/modules/sts.py
opr/modules/tdo.py
opr/modules/thr.py
opr/modules/udp.py
opr-310.dist-info/METADATA
opr-310.dist-info/WHEEL
opr-310.dist-info/entry_points.txt
opr-310.dist-info/top_level.txt
opr-310.dist-info/zip-safe
opr-310.dist-info/RECORD
