Metadata-Version: 2.1
Name: opr
Version: 310
Summary: Object Programming Runtime
Author-email: Bart Thate <bthate@dds.nl>
License: Public Domain
Project-URL: home, https://pypi.org/project/opr
Project-URL: bugs, https://github.com/bthate/opr/issues
Project-URL: source, https://github.com/bthate/opr
Classifier: Development Status :: 3 - Alpha
Classifier: License :: Public Domain
Classifier: Operating System :: Unix
Classifier: Programming Language :: Python
Classifier: Topic :: Utilities
Provides-Extra: dev
